{
  "hash": "a64603f5",
  "configHash": "40032149",
  "lockfileHash": "7a79bcce",
  "browserHash": "224865da",
  "optimized": {
    "vue": {
      "src": "../../../../node_modules/vue/dist/vue.runtime.esm-bundler.js",
      "file": "vue.js",
      "fileHash": "4bf01a03",
      "needsInterop": false
    },
    "vitepress > @vue/devtools-api": {
      "src": "../../../../node_modules/@vue/devtools-api/dist/index.js",
      "file": "vitepress___@vue_devtools-api.js",
      "fileHash": "71d8f32d",
      "needsInterop": false
    },
    "vitepress > @vueuse/core": {
      "src": "../../../../node_modules/@vueuse/core/index.mjs",
      "file": "vitepress___@vueuse_core.js",
      "fileHash": "43f151eb",
      "needsInterop": false
    },
    "vitepress > @vueuse/integrations/useFocusTrap": {
      "src": "../../../../node_modules/@vueuse/integrations/useFocusTrap.mjs",
      "file": "vitepress___@vueuse_integrations_useFocusTrap.js",
      "fileHash": "53bf5105",
      "needsInterop": false
    },
    "vitepress > mark.js/src/vanilla.js": {
      "src": "../../../../node_modules/mark.js/src/vanilla.js",
      "file": "vitepress___mark__js_src_vanilla__js.js",
      "fileHash": "2e4ff400",
      "needsInterop": false
    },
    "vitepress > minisearch": {
      "src": "../../../../node_modules/minisearch/dist/es/index.js",
      "file": "vitepress___minisearch.js",
      "fileHash": "100227d0",
      "needsInterop": false
    },
    "vitepress-theme-teek": {
      "src": "../../../../node_modules/vitepress-theme-teek/es/index.mjs",
      "file": "vitepress-theme-teek.js",
      "fileHash": "d2b8716b",
      "needsInterop": false
    }
  },
  "chunks": {
    "chunk-KUBE56QH": {
      "file": "chunk-KUBE56QH.js"
    },
    "chunk-RWXOEYSZ": {
      "file": "chunk-RWXOEYSZ.js"
    },
    "chunk-PZ5AY32C": {
      "file": "chunk-PZ5AY32C.js"
    }
  }
}